neural_logic_machine/__init__.py
neural_logic_machine/padded_NLM.py
neural_logic_machine/unpadded_NLM.py
neural_logic_machine-1.1.0.dist-info/LICENSE
neural_logic_machine-1.1.0.dist-info/METADATA
neural_logic_machine-1.1.0.dist-info/WHEEL
neural_logic_machine-1.1.0.dist-info/top_level.txt
neural_logic_machine-1.1.0.dist-info/RECORD
