Metadata-Version: 2.1
Name: neural-logic-machine
Version: 1.1.0
Summary: A simple implementation of Neural Logic Machines in Pytorch.
Author: Masataro Asai
Author-email: Carlos Núñez Molina <ccaarlos@ugr.es>
License: MIT License
Project-URL: Homepage, https://github.com/TheAeryan/simple-NLM
Keywords: machine-learning,statistics,pytorch,automated-planning
Classifier: License :: OSI Approved :: MIT License
Classifier: Programming Language :: Python
Classifier: Programming Language :: Python :: 3
License-File: LICENSE
Requires-Dist: torch
